README
setup.py
httpexceptor/__init__.py
httpexceptor.egg-info/PKG-INFO
httpexceptor.egg-info/SOURCES.txt
httpexceptor.egg-info/dependency_links.txt
httpexceptor.egg-info/not-zip-safe
httpexceptor.egg-info/requires.txt
httpexceptor.egg-info/top_level.txt
test/test_main.py