Metadata-Version: 1.1
Name: httpexceptor
Version: 1.3.1
Summary: WSGI middleware to handle HTTP responses using exceptions
Home-page: https://github.com/tiddlyweb/httpexceptor
Author: FND
Author-email: cdent@peermore.com
License: LICENSE
Platform: Posix; MacOS X; Windows
Classifier: Environment :: Web Environment
Classifier: Intended Audience :: Developers
Classifier: License :: OSI Approved :: BSD License
Classifier: Operating System :: OS Independent
Classifier: Programming Language :: Python :: 2.6
Classifier: Programming Language :: Python :: 2.7
Classifier: Programming Language :: Python :: 3.2
Classifier: Programming Language :: Python :: 3.3
Classifier: Topic :: Internet :: WWW/HTTP :: WSGI :: Middleware
